litexcnc/__init__.py
litexcnc/__main__.py
litexcnc/cli/__init__.py
litexcnc/cli/build_firmware.py
litexcnc/cli/config/hub75hat-rpi5.cfg
litexcnc/cli/config/hub75hat.cfg
litexcnc/cli/convert_bit_to_flash.py
litexcnc/cli/flash_firmware.py
litexcnc/cli/install_driver.py
litexcnc/cli/install_litex.py
litexcnc/cli/install_toolchain.py
litexcnc/config/__init__.py
litexcnc/config/boards/__init__.py
litexcnc/config/boards/colorlight.py
litexcnc/config/boards/rv901t.py
litexcnc/config/connections/__init__.py
litexcnc/config/connections/etherbone.py
litexcnc/config/connections/spi.py
litexcnc/config/modules/__init__.py
litexcnc/config/modules/encoder.py
litexcnc/config/modules/gpio.py
litexcnc/config/modules/pwm.py
litexcnc/config/modules/stepgen.py
litexcnc/config/modules/watchdog.py
litexcnc/driver/__init__.py
litexcnc/driver/boards/README.rst
litexcnc/driver/boards/etherbone.c
litexcnc/driver/boards/etherbone.h
litexcnc/driver/boards/janked/README.rst
litexcnc/driver/boards/janked/litexcnc_debug.c
litexcnc/driver/boards/janked/litexcnc_debug.h
litexcnc/driver/boards/litexcnc_eth.c
litexcnc/driver/boards/litexcnc_eth.h
litexcnc/driver/boards/litexcnc_pigpio.c
litexcnc/driver/boards/litexcnc_pigpio.h
litexcnc/driver/boards/litexcnc_pigpio_speed_test.c
litexcnc/driver/boards/litexcnc_spidev.c
litexcnc/driver/boards/litexcnc_spidev.h
litexcnc/driver/litexcnc.c
litexcnc/driver/litexcnc.h
litexcnc/driver/modules/README.rst
litexcnc/driver/modules/litexcnc_encoder.c
litexcnc/driver/modules/litexcnc_encoder.h
litexcnc/driver/modules/litexcnc_gpio.c
litexcnc/driver/modules/litexcnc_gpio.h
litexcnc/driver/modules/litexcnc_pwm.c
litexcnc/driver/modules/litexcnc_pwm.h
litexcnc/driver/modules/litexcnc_stepgen.c
litexcnc/driver/modules/litexcnc_stepgen.h
litexcnc/driver/wallclock.c
litexcnc/driver/wallclock.h
litexcnc/driver/watchdog.c
litexcnc/driver/watchdog.h
litexcnc/firmware/__init__.py
litexcnc/firmware/boards/__init__.py
litexcnc/firmware/boards/colorlight.py
litexcnc-1.3.4.dist-info/LICENSE
litexcnc-1.3.4.dist-info/METADATA
litexcnc-1.3.4.dist-info/WHEEL
litexcnc-1.3.4.dist-info/entry_points.txt
litexcnc-1.3.4.dist-info/RECORD
