Metadata-Version: 2.3
Name: litexcnc
Version: 1.3.4
Summary: Generic CNC firmware and driver for FPGA cards which are supported by LiteX
License: GPL-3.0-or-later
Keywords: FPGA,CNC,CNC-controller,CNC-machine,linuxcnc,linuxcnc-FPGA,litex
Author: Peter van Tol
Author-email: petertgvantol@gmail.com
Requires-Python: >=3.7,<3.13
Classifier: Development Status :: 3 - Alpha
Classifier: Environment :: Console
Classifier: Environment :: Other Environment
Classifier: License :: OSI Approved :: GNU General Public License v3 or later (GPLv3+)
Classifier: Natural Language :: English
Classifier: Operating System :: POSIX :: Linux
Classifier: Programming Language :: Other
Classifier: Programming Language :: Python :: 3 :: Only
Classifier: Programming Language :: Python :: 3.7
Classifier: Programming Language :: Python :: 3.8
Classifier: Programming Language :: Python :: 3.9
Classifier: Programming Language :: Python :: 3.10
Classifier: Topic :: Software Development :: Code Generators
Classifier: Topic :: System :: Hardware :: Hardware Drivers
Requires-Dist: chardet (>=5.0.0,<5.1.0)
Requires-Dist: click (>=8.1.3,<8.2.0)
Requires-Dist: meson (>=0.64.1,<0.65.0)
Requires-Dist: ninja (>=1.11.1,<1.12.0)
Requires-Dist: packaging (>=21.3)
Requires-Dist: pydantic (>=1.10.2,<2.0)
Requires-Dist: requests (>=2.28.1,<3.0)
Requires-Dist: yapps (>=2.2.0,<2.3.0)
